AUTHORS.txt
CHANGES.txt
LICENSE.txt
MANIFEST.in
README.md
TODO.txt
setup.py
django_mailqueue_backend.egg-info/PKG-INFO
django_mailqueue_backend.egg-info/SOURCES.txt
django_mailqueue_backend.egg-info/dependency_links.txt
django_mailqueue_backend.egg-info/requires.txt
django_mailqueue_backend.egg-info/top_level.txt
mailqueue_backend/__init__.py
mailqueue_backend/models.py
mailqueue_backend/settings.py
mailqueue_backend/tests.py
mailqueue_backend/mail/__init__.py
mailqueue_backend/mail/smtp.py
mailqueue_backend/management/__init__.py
mailqueue_backend/management/commands/__init__.py
mailqueue_backend/management/commands/process_mail_queue.py