Metadata-Version: 1.1
Name: django-mailqueue-backend
Version: 0.1.0
Summary: Simple Mail Queuing Backend for Django
Home-page: https://bitbucket.org/dwaiter/django-mailqueue-backend
Author: Dwaiter.com
Author-email: dev@dwaiter.com
License: BSD
Keywords: django mail queue smtp backend
Platform: UNKNOWN
Classifier: Development Status :: 4 - Beta
Classifier: Environment :: Web Environment
Classifier: Framework :: Django
Classifier: Intended Audience :: Developers
Classifier: License :: OSI Approved :: BSD License
Classifier: Natural Language :: English
Classifier: Operating System :: OS Independent
Classifier: Programming Language :: Python
Classifier: Topic :: Communications :: Email
Classifier: Topic :: Utilities
Classifier: Framework :: Django
